AUTHORS
LICENSE
MANIFEST.in
README.rst
setup.cfg
setup.py
landa_django_rest_auth.egg-info/PKG-INFO
landa_django_rest_auth.egg-info/SOURCES.txt
landa_django_rest_auth.egg-info/dependency_links.txt
landa_django_rest_auth.egg-info/not-zip-safe
landa_django_rest_auth.egg-info/requires.txt
landa_django_rest_auth.egg-info/top_level.txt
rest_auth/__init__.py
rest_auth/admin.py
rest_auth/app_settings.py
rest_auth/models.py
rest_auth/serializers.py
rest_auth/social_serializers.py
rest_auth/urls.py
rest_auth/utils.py
rest_auth/views.py
rest_auth/locale/cs/LC_MESSAGES/django.mo
rest_auth/locale/cs/LC_MESSAGES/django.po
rest_auth/locale/de/LC_MESSAGES/django.mo
rest_auth/locale/de/LC_MESSAGES/django.po
rest_auth/locale/es/LC_MESSAGES/django.mo
rest_auth/locale/es/LC_MESSAGES/django.po
rest_auth/locale/pl/LC_MESSAGES/django.mo
rest_auth/locale/pl/LC_MESSAGES/django.po
rest_auth/locale/ru/LC_MESSAGES/django.mo
rest_auth/locale/ru/LC_MESSAGES/django.po
rest_auth/registration/__init__.py
rest_auth/registration/app_settings.py
rest_auth/registration/serializers.py
rest_auth/registration/urls.py
rest_auth/registration/views.py
rest_auth/tests/__init__.py
rest_auth/tests/django_urls.py
rest_auth/tests/mixins.py
rest_auth/tests/requirements.pip
rest_auth/tests/settings.py
rest_auth/tests/test_api.py
rest_auth/tests/test_social.py
rest_auth/tests/urls.py